linked_roles/__init__.py
linked_roles/client.py
linked_roles/enums.py
linked_roles/errors.py
linked_roles/http.py
linked_roles/oauth2.py
linked_roles/role.py
linked_roles/user.py
linked_roles/utils.py
linked_roles-1.3.2.dist-info/LICENSE
linked_roles-1.3.2.dist-info/METADATA
linked_roles-1.3.2.dist-info/WHEEL
linked_roles-1.3.2.dist-info/top_level.txt
linked_roles-1.3.2.dist-info/RECORD
