Metadata-Version: 2.1
Name: linked-roles
Version: 1.3.2
Summary: A basic wrapper for the Discord Linked Roles OAuth2 API.
Home-page: https://github.com/staciax/discord-linked-roles
Author: staciax
License: MIT
Project-URL: Issue tracker, https://github.com/staciax/discord-linked-roles/issues
Classifier: License :: OSI Approved :: MIT License
Classifier: Intended Audience :: Developers
Classifier: Natural Language :: English
Classifier: Operating System :: OS Independent
Classifier: Programming Language :: Python :: 3
Classifier: Programming Language :: Python :: 3.8
Classifier: Programming Language :: Python :: 3.9
Classifier: Programming Language :: Python :: 3.10
Classifier: Programming Language :: Python :: 3.11
Requires-Python: >=3.8.0
License-File: LICENSE
Requires-Dist: aiohttp (<4,>=3.7.4)
